README.rst
setup.py
pyfea/__init__.py
pyfea/free_vibration.py
pyfea/galerkin_approx.py
pyfea.egg-info/PKG-INFO
pyfea.egg-info/SOURCES.txt
pyfea.egg-info/dependency_links.txt
pyfea.egg-info/not-zip-safe
pyfea.egg-info/top_level.txt