Metadata-Version: 1.1
Name: pyfea
Version: 1.0.0.dev1
Summary: Python Finite Element Analysis
Home-page: https://github.com/schang1146/pyfea
Author: team.pyfea
Author-email: team.pyfea@gmail.com
License: MIT
Keywords: engineering development analysis
Platform: UNKNOWN
Classifier: Development Status :: 3 - Alpha
Classifier: License :: OSI Approved :: MIT License
Classifier: Intended Audience :: Science/Research
Classifier: Topic :: Scientific/Engineering
Classifier: Programming Language :: Python :: 3
